[{"providerCode":3641659,"providerLocalicationCode":1354889,"providerName":"AVANCES TECNOLOGICOS EN NEUROCIRUGIA","networkCode":1,"networkDescription":"","observations":"","doctorType":0,"gender":"","collegiateCode":0,"onlineAppointment":false,"appointmentRequired":true,"videoConsultation":false,"tichCenterCode":0,"electronicPrescription":false,"providerType":4,"specialityInfo":{"specialityCode":28,"specialityDescription":"NEUROCIRUGÍA","subSpecialityCode":0,"subSpecialityDescription":null,"specialistName":"","specialityProviderCode":0},"contact":{"phone":"933800999","mobilePhone":"0","email":"","documentNumber":"B65279523"},"address":{"postalCode":null,"provinceCode":"","cityDescription":"","addressType":"","addressDescription":"BISBE SIVILLA","addressNumber":46,"doorway":"","floor":"","gateway":"","stair":"","latitude":0,"longitude":0},"tuotempo":{"centerCode":0,"providerCode":0,"onlineAppointment":false,"presentialAppointment":false,"videoAppointment":false,"phoneAppointment":false,"asisaLiveAppointment":false,"openHospital":false}},{"providerCode":3641659,"providerLocalicationCode":1354889,"providerName":"AVANCES TECNOLOGICOS EN NEUROCIRUGIA","networkCode":1,"networkDescription":"","observations":"","doctorType":1,"gender":"V","collegiateCode":282867573,"onlineAppointment":false,"appointmentRequired":true,"videoConsultation":false,"tichCenterCode":0,"electronicPrescription":false,"providerType":1,"specialityInfo":{"specialityCode":28,"specialityDescription":"NEUROCIRUGÍA","subSpecialityCode":0,"subSpecialityDescription":null,"specialistName":"ESPINOSA RODRIGUEZ, EDUARDO ENRIQUE","specialityProviderCode":3711864},"contact":{"phone":"933800999","mobilePhone":"0","email":"","documentNumber":"B65279523"},"address":{"postalCode":null,"provinceCode":"","cityDescription":"","addressType":"","addressDescription":"BISBE SIVILLA","addressNumber":46,"doorway":"","floor":"","gateway":"","stair":"","latitude":0,"longitude":0},"tuotempo":{"centerCode":0,"providerCode":0,"onlineAppointment":false,"presentialAppointment":false,"videoAppointment":false,"phoneAppointment":false,"asisaLiveAppointment":false,"openHospital":false}},{"providerCode":3641659,"providerLocalicationCode":1354889,"providerName":"AVANCES TECNOLOGICOS EN NEUROCIRUGIA","networkCode":1,"networkDescription":"","observations":"","doctorType":1,"gender":"V","collegiateCode":80833698,"onlineAppointment":false,"appointmentRequired":true,"videoConsultation":false,"tichCenterCode":0,"electronicPrescription":false,"providerType":1,"specialityInfo":{"specialityCode":28,"specialityDescription":"NEUROCIRUGÍA","subSpecialityCode":0,"subSpecialityDescription":null,"specialistName":"GUILLEN QUESADA, ANTONIO","specialityProviderCode":3770782},"contact":{"phone":"933800999","mobilePhone":"0","email":"","documentNumber":"B65279523"},"address":{"postalCode":null,"provinceCode":"","cityDescription":"","addressType":"","addressDescription":"BISBE SIVILLA","addressNumber":46,"doorway":"","floor":"","gateway":"","stair":"","latitude":0,"longitude":0},"tuotempo":{"centerCode":0,"providerCode":0,"onlineAppointment":false,"presentialAppointment":false,"videoAppointment":false,"phoneAppointment":false,"asisaLiveAppointment":false,"openHospital":false}},{"providerCode":3641659,"providerLocalicationCode":1354889,"providerName":"AVANCES TECNOLOGICOS EN NEUROCIRUGIA","networkCode":1,"networkDescription":"","observations":"","doctorType":1,"gender":"H","collegiateCode":80842296,"onlineAppointment":false,"appointmentRequired":true,"videoConsultation":false,"tichCenterCode":0,"electronicPrescription":false,"providerType":1,"specialityInfo":{"specialityCode":28,"specialityDescription":"NEUROCIRUGÍA","subSpecialityCode":0,"subSpecialityDescription":null,"specialistName":"PUERTA ROLDAN, PATRICIA","specialityProviderCode":3848685},"contact":{"phone":"933800999","mobilePhone":"0","email":"","documentNumber":"B65279523"},"address":{"postalCode":null,"provinceCode":"","cityDescription":"","addressType":"","addressDescription":"BISBE SIVILLA","addressNumber":46,"doorway":"","floor":"","gateway":"","stair":"","latitude":0,"longitude":0},"tuotempo":{"centerCode":0,"providerCode":0,"onlineAppointment":false,"presentialAppointment":false,"videoAppointment":false,"phoneAppointment":false,"asisaLiveAppointment":false,"openHospital":false}},{"providerCode":3641659,"providerLocalicationCode":1354889,"providerName":"AVANCES TECNOLOGICOS EN NEUROCIRUGIA","networkCode":1,"networkDescription":"","observations":"","doctorType":1,"gender":"V","collegiateCode":80862877,"onlineAppointment":false,"appointmentRequired":true,"videoConsultation":false,"tichCenterCode":0,"electronicPrescription":false,"providerType":1,"specialityInfo":{"specialityCode":28,"specialityDescription":"NEUROCIRUGÍA","subSpecialityCode":0,"subSpecialityDescription":null,"specialistName":"SANCHEZ PEÑA, JOSE GREGORIO","specialityProviderCode":3905601},"contact":{"phone":"933800999","mobilePhone":"0","email":"","documentNumber":"B65279523"},"address":{"postalCode":null,"provinceCode":"","cityDescription":"","addressType":"","addressDescription":"BISBE SIVILLA","addressNumber":46,"doorway":"","floor":"","gateway":"","stair":"","latitude":0,"longitude":0},"tuotempo":{"centerCode":0,"providerCode":0,"onlineAppointment":false,"presentialAppointment":false,"videoAppointment":false,"phoneAppointment":false,"asisaLiveAppointment":false,"openHospital":false}},{"providerCode":3641662,"providerLocalicationCode":1354889,"providerName":"AVANCES TECNOLOGICOS EN NEUROCIRUGIA","networkCode":1,"networkDescription":"","observations":"","doctorType":0,"gender":"","collegiateCode":0,"onlineAppointment":false,"appointmentRequired":true,"videoConsultation":false,"tichCenterCode":0,"electronicPrescription":false,"providerType":4,"specialityInfo":{"specialityCode":30,"specialityDescription":"NEUROLOGÍA","subSpecialityCode":0,"subSpecialityDescription":null,"specialistName":"","specialityProviderCode":0},"contact":{"phone":"933800999","mobilePhone":"0","email":"","documentNumber":"B65279523"},"address":{"postalCode":null,"provinceCode":"","cityDescription":"","addressType":"","addressDescription":"BISBE SIVILLA","addressNumber":46,"doorway":"","floor":"","gateway":"","stair":"","latitude":0,"longitude":0},"tuotempo":{"centerCode":0,"providerCode":0,"onlineAppointment":false,"presentialAppointment":false,"videoAppointment":false,"phoneAppointment":false,"asisaLiveAppointment":false,"openHospital":false}},{"providerCode":3641662,"providerLocalicationCode":1354889,"providerName":"AVANCES TECNOLOGICOS EN NEUROCIRUGIA","networkCode":1,"networkDescription":"","observations":"","doctorType":1,"gender":"V","collegiateCode":80851516,"onlineAppointment":false,"appointmentRequired":true,"videoConsultation":false,"tichCenterCode":0,"electronicPrescription":false,"providerType":1,"specialityInfo":{"specialityCode":30,"specialityDescription":"NEUROLOGÍA","subSpecialityCode":0,"subSpecialityDescription":null,"specialistName":"CASCALES LAHOZ, DIEGO","specialityProviderCode":3917015},"contact":{"phone":"933800999","mobilePhone":"0","email":"","documentNumber":"B65279523"},"address":{"postalCode":null,"provinceCode":"","cityDescription":"","addressType":"","addressDescription":"BISBE SIVILLA","addressNumber":46,"doorway":"","floor":"","gateway":"","stair":"","latitude":0,"longitude":0},"tuotempo":{"centerCode":0,"providerCode":0,"onlineAppointment":false,"presentialAppointment":false,"videoAppointment":false,"phoneAppointment":false,"asisaLiveAppointment":false,"openHospital":false}}]