[{"providerCode":3983472,"providerLocalicationCode":1610156,"providerName":"DELGADO GONZALEZ, ALMUDENA","networkCode":1,"networkDescription":"","observations":"","doctorType":0,"gender":"","collegiateCode":282875256,"onlineAppointment":true,"appointmentRequired":true,"videoConsultation":false,"tichCenterCode":2810,"electronicPrescription":false,"providerType":1,"specialityInfo":{"specialityCode":3,"specialityDescription":"ALERGOLOGÍA","subSpecialityCode":0,"subSpecialityDescription":null,"specialistName":"","specialityProviderCode":0},"contact":{"phone":"917581196","mobilePhone":"0","email":"","documentNumber":"02712703Z"},"address":{"postalCode":null,"provinceCode":"","cityDescription":"","addressType":"","addressDescription":"VALLADOLID","addressNumber":83,"doorway":"","floor":"","gateway":"","stair":"","latitude":0,"longitude":0},"tuotempo":{"centerCode":1610156,"providerCode":0,"onlineAppointment":true,"presentialAppointment":true,"videoAppointment":false,"phoneAppointment":false,"asisaLiveAppointment":false,"openHospital":true}}]