[{"providerCode":2412287,"providerLocalicationCode":388519,"providerName":"SAUCEDO FERNANDEZ, MATILDE","networkCode":1,"networkDescription":"","observations":"","doctorType":0,"gender":"","collegiateCode":464614745,"onlineAppointment":false,"appointmentRequired":true,"videoConsultation":false,"tichCenterCode":0,"electronicPrescription":true,"providerType":1,"specialityInfo":{"specialityCode":1,"specialityDescription":"MEDICINA GENERAL","subSpecialityCode":0,"subSpecialityDescription":null,"specialistName":"","specialityProviderCode":0},"contact":{"phone":"963855555","mobilePhone":"0","email":"","documentNumber":"22649559X"},"address":{"postalCode":null,"provinceCode":"","cityDescription":"","addressType":"","addressDescription":"BON ORDE","addressNumber":11,"doorway":"","floor":"B","gateway":"","stair":"","latitude":0,"longitude":0},"tuotempo":{"centerCode":0,"providerCode":0,"onlineAppointment":false,"presentialAppointment":false,"videoAppointment":false,"phoneAppointment":false,"asisaLiveAppointment":false,"openHospital":false}}]