[{"providerCode":2770723,"providerLocalicationCode":736998,"providerName":"BARAJAS LOZANO, VALENTIN","networkCode":1,"networkDescription":"","observations":"","doctorType":0,"gender":"","collegiateCode":282825243,"onlineAppointment":false,"appointmentRequired":false,"videoConsultation":false,"tichCenterCode":0,"electronicPrescription":true,"providerType":1,"specialityInfo":{"specialityCode":1,"specialityDescription":"MEDICINA GENERAL","subSpecialityCode":0,"subSpecialityDescription":null,"specialistName":"","specialityProviderCode":0},"contact":{"phone":"917966214","mobilePhone":"0","email":"","documentNumber":"50791660R"},"address":{"postalCode":null,"provinceCode":"","cityDescription":"","addressType":"","addressDescription":"ESPERANZA MACARENA","addressNumber":13,"doorway":"","floor":"BAJO","gateway":"","stair":"","latitude":0,"longitude":0},"tuotempo":{"centerCode":0,"providerCode":0,"onlineAppointment":false,"presentialAppointment":false,"videoAppointment":false,"phoneAppointment":false,"asisaLiveAppointment":false,"openHospital":false}}]