[{"providerCode":2851509,"providerLocalicationCode":814834,"providerName":"BORDEL NIETO, IGNACIO","networkCode":1,"networkDescription":"","observations":"","doctorType":0,"gender":"","collegiateCode":282842333,"onlineAppointment":false,"appointmentRequired":true,"videoConsultation":false,"tichCenterCode":0,"electronicPrescription":true,"providerType":1,"specialityInfo":{"specialityCode":19,"specialityDescription":"ESTOMATOLOGÍA","subSpecialityCode":0,"subSpecialityDescription":null,"specialistName":"","specialityProviderCode":0},"contact":{"phone":"913784348","mobilePhone":"0","email":"","documentNumber":"05265805R"},"address":{"postalCode":null,"provinceCode":"","cityDescription":"","addressType":"","addressDescription":"COLLADO DE MARICHIVA","addressNumber":2,"doorway":"","floor":"1º, C","gateway":"","stair":"","latitude":0,"longitude":0},"tuotempo":{"centerCode":0,"providerCode":0,"onlineAppointment":false,"presentialAppointment":false,"videoAppointment":false,"phoneAppointment":false,"asisaLiveAppointment":false,"openHospital":false}}]