[{"providerCode":2960236,"providerLocalicationCode":891703,"providerName":"CLINICA HLA MONTPELLIER","parentCode":0,"parentDescription":"","networkCode":1,"networkDescription":"","distance":4612.11,"electronicPrescription":false,"appointmentRequired":true,"providerType":3,"doctorType":7,"businessGroup":true,"onlineAppointment":true,"videoConsultation":false,"specialityInfo":{"specialityCode":16,"specialityDescription":"DERMATOLOGÍA MÉDICO-QUIRÚRGICA Y VENEREO","subSpecialityCode":0,"subSpecialityDescription":"","specialistName":"","specialityProviderCode":0},"address":{"postalCode":"50012","provinceCode":"50","cityDescription":"ZARAGOZA","addressType":"VIA","addressDescription":"HISPANIDAD","addressNumber":37,"doorway":"","floor":"","gateway":"","stair":"","latitude":41.6358938,"longitude":-0.9134867},"contact":{"phone":"976351386","mobilePhone":"","email":"","documentNumber":"A50523554"},"professional":{"gender":"","collegiateCode":0,"collegiateAut":""},"tuotempo":{"centerCode":891703,"providerCode":0,"onlineAppointment":true,"presentialAppointment":true,"videoAppointment":false,"phoneAppointment":false,"asisaLiveAppointment":false,"openHospital":false},"languages":[]},{"providerCode":3751044,"providerLocalicationCode":1429422,"providerName":"ZUBIRI ARA, MARIA LUISA","parentCode":891703,"parentDescription":"CLINICA HLA MONTPELLIER","networkCode":1,"networkDescription":"","distance":4612.11,"electronicPrescription":true,"appointmentRequired":true,"providerType":1,"doctorType":1,"businessGroup":true,"onlineAppointment":false,"videoConsultation":false,"specialityInfo":{"specialityCode":16,"specialityDescription":"DERMATOLOGÍA MÉDICO-QUIRÚRGICA Y VENEREO","subSpecialityCode":0,"subSpecialityDescription":"","specialistName":"","specialityProviderCode":0},"address":{"postalCode":"50012","provinceCode":"50","cityDescription":"ZARAGOZA","addressType":"VIA","addressDescription":"HISPANIDAD","addressNumber":37,"doorway":"","floor":"","gateway":"","stair":"","latitude":41.6358938,"longitude":-0.9134867},"contact":{"phone":"976351386","mobilePhone":"","email":"","documentNumber":"17686663P"},"professional":{"gender":"H","collegiateCode":505007967,"collegiateAut":""},"tuotempo":{"centerCode":0,"providerCode":0,"onlineAppointment":false,"presentialAppointment":false,"videoAppointment":false,"phoneAppointment":false,"asisaLiveAppointment":false,"openHospital":false},"languages":[]},{"providerCode":3948750,"providerLocalicationCode":898710,"providerName":"HLA CENTRO MÉDICO ZARAGOZA","parentCode":0,"parentDescription":"","networkCode":1,"networkDescription":"","distance":4613.12,"electronicPrescription":false,"appointmentRequired":true,"providerType":4,"doctorType":7,"businessGroup":true,"onlineAppointment":false,"videoConsultation":false,"specialityInfo":{"specialityCode":16,"specialityDescription":"DERMATOLOGÍA MÉDICO-QUIRÚRGICA Y VENEREO","subSpecialityCode":0,"subSpecialityDescription":"","specialistName":"","specialityProviderCode":0},"address":{"postalCode":"50006","provinceCode":"50","cityDescription":"ZARAGOZA","addressType":"CALLE","addressDescription":"GRAN VIA","addressNumber":27,"doorway":"","floor":"","gateway":"","stair":"","latitude":41.6454113,"longitude":-0.8891866},"contact":{"phone":"976230703","mobilePhone":"","email":"","documentNumber":"B50457134"},"professional":{"gender":"","collegiateCode":0,"collegiateAut":""},"tuotempo":{"centerCode":0,"providerCode":0,"onlineAppointment":false,"presentialAppointment":false,"videoAppointment":false,"phoneAppointment":false,"asisaLiveAppointment":false,"openHospital":false},"languages":[]},{"providerCode":4051578,"providerLocalicationCode":1666348,"providerName":"CONEJERO DEL MAZO, CLAUDIA","parentCode":898710,"parentDescription":"HLA CENTRO MÉDICO ZARAGOZA","networkCode":1,"networkDescription":"","distance":4613.12,"electronicPrescription":true,"appointmentRequired":true,"providerType":1,"doctorType":1,"businessGroup":true,"onlineAppointment":false,"videoConsultation":false,"specialityInfo":{"specialityCode":16,"specialityDescription":"DERMATOLOGÍA MÉDICO-QUIRÚRGICA Y VENEREO","subSpecialityCode":0,"subSpecialityDescription":"","specialistName":"","specialityProviderCode":0},"address":{"postalCode":"50006","provinceCode":"50","cityDescription":"ZARAGOZA","addressType":"CALLE","addressDescription":"GRAN VIA","addressNumber":27,"doorway":"","floor":"","gateway":"","stair":"","latitude":41.6454113,"longitude":-0.8891866},"contact":{"phone":"976230703","mobilePhone":"","email":"","documentNumber":"72984396Z"},"professional":{"gender":"H","collegiateCode":505014931,"collegiateAut":""},"tuotempo":{"centerCode":0,"providerCode":0,"onlineAppointment":false,"presentialAppointment":false,"videoAppointment":false,"phoneAppointment":false,"asisaLiveAppointment":false,"openHospital":false},"languages":[]},{"providerCode":3571415,"providerLocalicationCode":1222975,"providerName":"HOSPITAL QUIRONSALUD  ZARAGOZA FLORESTA","parentCode":0,"parentDescription":"","networkCode":1,"networkDescription":"","distance":4612.59,"electronicPrescription":false,"appointmentRequired":true,"providerType":4,"doctorType":7,"businessGroup":true,"onlineAppointment":true,"videoConsultation":false,"specialityInfo":{"specialityCode":16,"specialityDescription":"DERMATOLOGÍA MÉDICO-QUIRÚRGICA Y VENEREO","subSpecialityCode":0,"subSpecialityDescription":"","specialistName":"","specialityProviderCode":0},"address":{"postalCode":"50012","provinceCode":"50","cityDescription":"ZARAGOZA","addressType":"AVENIDA","addressDescription":"ALCALDE GOMEZ LAGUNA","addressNumber":82,"doorway":"","floor":"","gateway":"","stair":"","latitude":41.64007,"longitude":-0.91775},"contact":{"phone":"976579000","mobilePhone":"","email":"","documentNumber":"B87324844"},"professional":{"gender":"","collegiateCode":0,"collegiateAut":""},"tuotempo":{"centerCode":1222975,"providerCode":0,"onlineAppointment":true,"presentialAppointment":true,"videoAppointment":false,"phoneAppointment":false,"asisaLiveAppointment":false,"openHospital":false},"languages":[]},{"providerCode":4039323,"providerLocalicationCode":1656158,"providerName":"CONEJERO DEL MAZO, CLAUDIA","parentCode":0,"parentDescription":"","networkCode":1,"networkDescription":"","distance":4613.12,"electronicPrescription":true,"appointmentRequired":true,"providerType":1,"doctorType":1,"businessGroup":false,"onlineAppointment":false,"videoConsultation":false,"specialityInfo":{"specialityCode":16,"specialityDescription":"DERMATOLOGÍA MÉDICO-QUIRÚRGICA Y VENEREO","subSpecialityCode":0,"subSpecialityDescription":"","specialistName":"","specialityProviderCode":0},"address":{"postalCode":"50006","provinceCode":"50","cityDescription":"ZARAGOZA","addressType":"CALLE","addressDescription":"GRAN VIA","addressNumber":27,"doorway":"","floor":"","gateway":"","stair":"","latitude":41.6454113,"longitude":-0.8891866},"contact":{"phone":"976230703","mobilePhone":"","email":"","documentNumber":"72984396Z"},"professional":{"gender":"H","collegiateCode":505014931,"collegiateAut":""},"tuotempo":{"centerCode":0,"providerCode":0,"onlineAppointment":false,"presentialAppointment":false,"videoAppointment":false,"phoneAppointment":false,"asisaLiveAppointment":false,"openHospital":false},"languages":[]},{"providerCode":4045061,"providerLocalicationCode":1661040,"providerName":"DEL PRADO SANZ, ELENA","parentCode":1222975,"parentDescription":"HOSPITAL QUIRONSALUD  ZARAGOZA FLORESTA","networkCode":1,"networkDescription":"","distance":4612.59,"electronicPrescription":true,"appointmentRequired":true,"providerType":1,"doctorType":1,"businessGroup":false,"onlineAppointment":false,"videoConsultation":false,"specialityInfo":{"specialityCode":16,"specialityDescription":"DERMATOLOGÍA MÉDICO-QUIRÚRGICA Y VENEREO","subSpecialityCode":0,"subSpecialityDescription":"","specialistName":"","specialityProviderCode":0},"address":{"postalCode":"50012","provinceCode":"50","cityDescription":"ZARAGOZA","addressType":"AVENIDA","addressDescription":"ALCALDE GOMEZ LAGUNA","addressNumber":82,"doorway":"","floor":"","gateway":"","stair":"","latitude":41.64007,"longitude":-0.91775},"contact":{"phone":"976579000","mobilePhone":"","email":"","documentNumber":"16803853F"},"professional":{"gender":"H","collegiateCode":504202362,"collegiateAut":""},"tuotempo":{"centerCode":0,"providerCode":0,"onlineAppointment":false,"presentialAppointment":false,"videoAppointment":false,"phoneAppointment":false,"asisaLiveAppointment":false,"openHospital":false},"languages":[]},{"providerCode":3984576,"providerLocalicationCode":1611191,"providerName":"BERGUA RUEDA, PAULA","parentCode":1222975,"parentDescription":"HOSPITAL QUIRONSALUD  ZARAGOZA FLORESTA","networkCode":1,"networkDescription":"","distance":4612.59,"electronicPrescription":true,"appointmentRequired":true,"providerType":1,"doctorType":1,"businessGroup":false,"onlineAppointment":false,"videoConsultation":false,"specialityInfo":{"specialityCode":16,"specialityDescription":"DERMATOLOGÍA MÉDICO-QUIRÚRGICA Y VENEREO","subSpecialityCode":0,"subSpecialityDescription":"","specialistName":"","specialityProviderCode":0},"address":{"postalCode":"50012","provinceCode":"50","cityDescription":"ZARAGOZA","addressType":"AVENIDA","addressDescription":"ALCALDE GOMEZ LAGUNA","addressNumber":82,"doorway":"","floor":"","gateway":"","stair":"","latitude":41.64007,"longitude":-0.91775},"contact":{"phone":"976579000","mobilePhone":"","email":"","documentNumber":"17741072E"},"professional":{"gender":"H","collegiateCode":500834095,"collegiateAut":""},"tuotempo":{"centerCode":0,"providerCode":0,"onlineAppointment":false,"presentialAppointment":false,"videoAppointment":false,"phoneAppointment":false,"asisaLiveAppointment":false,"openHospital":false},"languages":[]},{"providerCode":3984707,"providerLocalicationCode":1611322,"providerName":"RIVERA RODRIGUEZ, ALVARO","parentCode":1222975,"parentDescription":"HOSPITAL QUIRONSALUD  ZARAGOZA FLORESTA","networkCode":1,"networkDescription":"","distance":4612.59,"electronicPrescription":true,"appointmentRequired":true,"providerType":1,"doctorType":1,"businessGroup":false,"onlineAppointment":false,"videoConsultation":false,"specialityInfo":{"specialityCode":16,"specialityDescription":"DERMATOLOGÍA MÉDICO-QUIRÚRGICA Y VENEREO","subSpecialityCode":0,"subSpecialityDescription":"","specialistName":"","specialityProviderCode":0},"address":{"postalCode":"50012","provinceCode":"50","cityDescription":"ZARAGOZA","addressType":"AVENIDA","addressDescription":"ALCALDE GOMEZ LAGUNA","addressNumber":82,"doorway":"","floor":"","gateway":"","stair":"","latitude":41.64007,"longitude":-0.91775},"contact":{"phone":"976579000","mobilePhone":"","email":"","documentNumber":"71662138A"},"professional":{"gender":"V","collegiateCode":505015432,"collegiateAut":""},"tuotempo":{"centerCode":0,"providerCode":0,"onlineAppointment":false,"presentialAppointment":false,"videoAppointment":false,"phoneAppointment":false,"asisaLiveAppointment":false,"openHospital":false},"languages":[]},{"providerCode":3984781,"providerLocalicationCode":1611410,"providerName":"SOLANAS TREVIÑO, RUTH","parentCode":1222975,"parentDescription":"HOSPITAL QUIRONSALUD  ZARAGOZA FLORESTA","networkCode":1,"networkDescription":"","distance":4612.59,"electronicPrescription":true,"appointmentRequired":true,"providerType":1,"doctorType":1,"businessGroup":false,"onlineAppointment":false,"videoConsultation":false,"specialityInfo":{"specialityCode":16,"specialityDescription":"DERMATOLOGÍA MÉDICO-QUIRÚRGICA Y VENEREO","subSpecialityCode":0,"subSpecialityDescription":"","specialistName":"","specialityProviderCode":0},"address":{"postalCode":"50012","provinceCode":"50","cityDescription":"ZARAGOZA","addressType":"AVENIDA","addressDescription":"ALCALDE GOMEZ LAGUNA","addressNumber":82,"doorway":"","floor":"","gateway":"","stair":"","latitude":41.64007,"longitude":-0.91775},"contact":{"phone":"976579000","mobilePhone":"","email":"","documentNumber":"25475673E"},"professional":{"gender":"H","collegiateCode":505015119,"collegiateAut":""},"tuotempo":{"centerCode":0,"providerCode":0,"onlineAppointment":false,"presentialAppointment":false,"videoAppointment":false,"phoneAppointment":false,"asisaLiveAppointment":false,"openHospital":false},"languages":[]},{"providerCode":3806135,"providerLocalicationCode":1468739,"providerName":"MOLINS RUIZ, MARTA","parentCode":0,"parentDescription":"","networkCode":1,"networkDescription":"","distance":4612.59,"electronicPrescription":true,"appointmentRequired":true,"providerType":1,"doctorType":1,"businessGroup":false,"onlineAppointment":false,"videoConsultation":false,"specialityInfo":{"specialityCode":16,"specialityDescription":"DERMATOLOGÍA MÉDICO-QUIRÚRGICA Y VENEREO","subSpecialityCode":0,"subSpecialityDescription":"","specialistName":"","specialityProviderCode":0},"address":{"postalCode":"50012","provinceCode":"50","cityDescription":"ZARAGOZA","addressType":"AVENIDA","addressDescription":"ALCALDE GOMEZ LAGUNA","addressNumber":82,"doorway":"","floor":"","gateway":"","stair":"","latitude":41.64007,"longitude":-0.91775},"contact":{"phone":"976579000","mobilePhone":"","email":"","documentNumber":"73006974Y"},"professional":{"gender":"H","collegiateCode":505015466,"collegiateAut":""},"tuotempo":{"centerCode":0,"providerCode":0,"onlineAppointment":false,"presentialAppointment":false,"videoAppointment":false,"phoneAppointment":false,"asisaLiveAppointment":false,"openHospital":false},"languages":[]},{"providerCode":3919952,"providerLocalicationCode":1558656,"providerName":"SOGUERO GARCIA, MARIA LUISA","parentCode":898710,"parentDescription":"HLA CENTRO MÉDICO ZARAGOZA","networkCode":1,"networkDescription":"","distance":4613.12,"electronicPrescription":true,"appointmentRequired":true,"providerType":1,"doctorType":1,"businessGroup":false,"onlineAppointment":false,"videoConsultation":false,"specialityInfo":{"specialityCode":16,"specialityDescription":"DERMATOLOGÍA MÉDICO-QUIRÚRGICA Y VENEREO","subSpecialityCode":0,"subSpecialityDescription":"","specialistName":"","specialityProviderCode":0},"address":{"postalCode":"50006","provinceCode":"50","cityDescription":"ZARAGOZA","addressType":"CALLE","addressDescription":"GRAN VIA","addressNumber":27,"doorway":"","floor":"","gateway":"","stair":"","latitude":41.6454113,"longitude":-0.8891866},"contact":{"phone":"976230703","mobilePhone":"","email":"","documentNumber":"25438963C"},"professional":{"gender":"H","collegiateCode":505011599,"collegiateAut":""},"tuotempo":{"centerCode":0,"providerCode":0,"onlineAppointment":false,"presentialAppointment":false,"videoAppointment":false,"phoneAppointment":false,"asisaLiveAppointment":false,"openHospital":false},"languages":[]},{"providerCode":3223084,"providerLocalicationCode":1106246,"providerName":"MULTICONSULTA","parentCode":0,"parentDescription":"","networkCode":1,"networkDescription":"","distance":4614.01,"electronicPrescription":false,"appointmentRequired":false,"providerType":4,"doctorType":7,"businessGroup":false,"onlineAppointment":false,"videoConsultation":false,"specialityInfo":{"specialityCode":16,"specialityDescription":"DERMATOLOGÍA MÉDICO-QUIRÚRGICA Y VENEREO","subSpecialityCode":0,"subSpecialityDescription":"","specialistName":"","specialityProviderCode":0},"address":{"postalCode":"50010","provinceCode":"50","cityDescription":"ZARAGOZA","addressType":"AVENIDA","addressDescription":"MADRID","addressNumber":155,"doorway":"","floor":"","gateway":"","stair":"","latitude":41.6531323,"longitude":-0.9051631},"contact":{"phone":"976321080","mobilePhone":"","email":"","documentNumber":"B50489632"},"professional":{"gender":"","collegiateCode":0,"collegiateAut":""},"tuotempo":{"centerCode":0,"providerCode":0,"onlineAppointment":false,"presentialAppointment":false,"videoAppointment":false,"phoneAppointment":false,"asisaLiveAppointment":false,"openHospital":false},"languages":[]},{"providerCode":3313581,"providerLocalicationCode":1159774,"providerName":"MARTINEZ SORIANO, SILVIA","parentCode":1106246,"parentDescription":"MULTICONSULTA","networkCode":1,"networkDescription":"","distance":4614.01,"electronicPrescription":false,"appointmentRequired":false,"providerType":1,"doctorType":1,"businessGroup":false,"onlineAppointment":false,"videoConsultation":false,"specialityInfo":{"specialityCode":16,"specialityDescription":"DERMATOLOGÍA MÉDICO-QUIRÚRGICA Y VENEREO","subSpecialityCode":0,"subSpecialityDescription":"","specialistName":"","specialityProviderCode":0},"address":{"postalCode":"50010","provinceCode":"50","cityDescription":"ZARAGOZA","addressType":"AVENIDA","addressDescription":"MADRID","addressNumber":155,"doorway":"","floor":"","gateway":"","stair":"","latitude":41.6531323,"longitude":-0.9051631},"contact":{"phone":"976321080","mobilePhone":"","email":"","documentNumber":"29132596Z"},"professional":{"gender":"H","collegiateCode":505014257,"collegiateAut":""},"tuotempo":{"centerCode":0,"providerCode":0,"onlineAppointment":false,"presentialAppointment":false,"videoAppointment":false,"phoneAppointment":false,"asisaLiveAppointment":false,"openHospital":false},"languages":[]}]