[{"providerCode":3674651,"providerLocalicationCode":1379857,"providerName":"SERVICIOS PODOACTIVA","parentCode":0,"parentDescription":"","networkCode":1,"networkDescription":"","distance":4666.74,"electronicPrescription":false,"appointmentRequired":true,"providerType":4,"doctorType":7,"businessGroup":false,"onlineAppointment":false,"videoConsultation":false,"specialityInfo":{"specialityCode":98,"specialityDescription":"PODOLOGÍA","subSpecialityCode":0,"subSpecialityDescription":"","specialistName":"","specialityProviderCode":0},"address":{"postalCode":22002,"provinceCode":"22","cityDescription":"HUESCA","addressType":"CALLE","addressDescription":"PADRE HUESCA","addressNumber":88,"doorway":"","floor":"","gateway":"","stair":"","latitude":42.1343397,"longitude":-0.40626},"contact":{"phone":"974231280","mobilePhone":"","email":"","documentNumber":"B22411375"},"professional":{"gender":"","collegiateCode":0,"collegiateAut":""},"languages":["EN"]},{"providerCode":2905961,"providerLocalicationCode":857231,"providerName":"CENTRO MEDICO SEAP","parentCode":0,"parentDescription":"","networkCode":1,"networkDescription":"","distance":4642.06,"electronicPrescription":false,"appointmentRequired":true,"providerType":4,"doctorType":7,"businessGroup":false,"onlineAppointment":false,"videoConsultation":false,"specialityInfo":{"specialityCode":98,"specialityDescription":"PODOLOGÍA","subSpecialityCode":0,"subSpecialityDescription":"","specialistName":"","specialityProviderCode":0},"address":{"postalCode":22400,"provinceCode":"22","cityDescription":"MONZON","addressType":"CALLE","addressDescription":"BARÓN DE EROLES","addressNumber":15,"doorway":"","floor":"","gateway":"","stair":"","latitude":41.91338,"longitude":0.19429},"contact":{"phone":"974404280","mobilePhone":"","email":"","documentNumber":"B22230056"},"professional":{"gender":"","collegiateCode":0,"collegiateAut":""},"languages":[]},{"providerCode":3479344,"providerLocalicationCode":1249473,"providerName":"CENTRO MEDICO POLIVALENTE","parentCode":0,"parentDescription":"","networkCode":1,"networkDescription":"","distance":4666.81,"electronicPrescription":false,"appointmentRequired":true,"providerType":4,"doctorType":7,"businessGroup":false,"onlineAppointment":false,"videoConsultation":false,"specialityInfo":{"specialityCode":98,"specialityDescription":"PODOLOGÍA","subSpecialityCode":0,"subSpecialityDescription":"","specialistName":"","specialityProviderCode":0},"address":{"postalCode":22002,"provinceCode":"22","cityDescription":"HUESCA","addressType":"CALLE","addressDescription":"ZARAGOZA","addressNumber":10,"doorway":"","floor":"BAJOS","gateway":"","stair":"","latitude":42.13495,"longitude":-0.40914},"contact":{"phone":"974210227","mobilePhone":"","email":"","documentNumber":"B22383004"},"professional":{"gender":"","collegiateCode":0,"collegiateAut":""},"languages":[]},{"providerCode":3968853,"providerLocalicationCode":1599073,"providerName":"GRACIA GALLARDO, MARIA","parentCode":0,"parentDescription":"","networkCode":1,"networkDescription":"","distance":4666.81,"electronicPrescription":false,"appointmentRequired":true,"providerType":1,"doctorType":6,"businessGroup":false,"onlineAppointment":false,"videoConsultation":false,"specialityInfo":{"specialityCode":98,"specialityDescription":"PODOLOGÍA","subSpecialityCode":0,"subSpecialityDescription":"","specialistName":"","specialityProviderCode":0},"address":{"postalCode":22002,"provinceCode":"22","cityDescription":"HUESCA","addressType":"CALLE","addressDescription":"ZARAGOZA","addressNumber":10,"doorway":"","floor":"","gateway":"","stair":"","latitude":42.134945,"longitude":-0.4091391},"contact":{"phone":"974210227","mobilePhone":"","email":"","documentNumber":"18041807D"},"professional":{"gender":"H","collegiateCode":505000142,"collegiateAut":""},"languages":[]},{"providerCode":3243116,"providerLocalicationCode":1114759,"providerName":"MENDEZ GALLARDO, ANGEL","parentCode":0,"parentDescription":"","networkCode":1,"networkDescription":"","distance":4715.87,"electronicPrescription":false,"appointmentRequired":true,"providerType":1,"doctorType":6,"businessGroup":false,"onlineAppointment":false,"videoConsultation":false,"specialityInfo":{"specialityCode":98,"specialityDescription":"PODOLOGÍA","subSpecialityCode":0,"subSpecialityDescription":"","specialistName":"","specialityProviderCode":0},"address":{"postalCode":22700,"provinceCode":"22","cityDescription":"JACA","addressType":"AVENIDA","addressDescription":"JUAN XXIII","addressNumber":19,"doorway":"","floor":"BAJO","gateway":"","stair":"","latitude":42.57537,"longitude":-0.54682},"contact":{"phone":"974364917","mobilePhone":"","email":"","documentNumber":"11822395G"},"professional":{"gender":"V","collegiateCode":505000256,"collegiateAut":""},"languages":[]},{"providerCode":3745436,"providerLocalicationCode":1424515,"providerName":"MEDICA FRAGA","parentCode":0,"parentDescription":"","networkCode":1,"networkDescription":"","distance":4598.7,"electronicPrescription":false,"appointmentRequired":true,"providerType":4,"doctorType":7,"businessGroup":false,"onlineAppointment":false,"videoConsultation":false,"specialityInfo":{"specialityCode":98,"specialityDescription":"PODOLOGÍA","subSpecialityCode":0,"subSpecialityDescription":"","specialistName":"","specialityProviderCode":0},"address":{"postalCode":22520,"provinceCode":"22","cityDescription":"FRAGA","addressType":"CALLE","addressDescription":"AGUSTINA DE ARAGÓN","addressNumber":22,"doorway":"","floor":"","gateway":"","stair":"","latitude":41.52226,"longitude":0.33534},"contact":{"phone":"974471907","mobilePhone":"","email":"","documentNumber":"B22129969"},"professional":{"gender":"","collegiateCode":0,"collegiateAut":""},"languages":[]},{"providerCode":3257698,"providerLocalicationCode":1124529,"providerName":"CENTRO ASISTENCIAL LITERA SALUD","parentCode":0,"parentDescription":"","networkCode":1,"networkDescription":"","distance":4635.03,"electronicPrescription":false,"appointmentRequired":true,"providerType":4,"doctorType":7,"businessGroup":false,"onlineAppointment":false,"videoConsultation":false,"specialityInfo":{"specialityCode":98,"specialityDescription":"PODOLOGÍA","subSpecialityCode":0,"subSpecialityDescription":"","specialistName":"","specialityProviderCode":0},"address":{"postalCode":22500,"provinceCode":"22","cityDescription":"BINEFAR","addressType":"AVENIDA","addressDescription":"ARAGÓN","addressNumber":50,"doorway":"","floor":"BJ","gateway":"","stair":"","latitude":41.84969,"longitude":0.29169},"contact":{"phone":"974431950","mobilePhone":"","email":"","documentNumber":"B22252688"},"professional":{"gender":"","collegiateCode":0,"collegiateAut":""},"languages":[]},{"providerCode":3342956,"providerLocalicationCode":1157114,"providerName":"POLICLINICA SOMONTANO","parentCode":0,"parentDescription":"","networkCode":1,"networkDescription":"","distance":4655.84,"electronicPrescription":false,"appointmentRequired":true,"providerType":4,"doctorType":7,"businessGroup":false,"onlineAppointment":false,"videoConsultation":false,"specialityInfo":{"specialityCode":98,"specialityDescription":"PODOLOGÍA","subSpecialityCode":0,"subSpecialityDescription":"","specialistName":"","specialityProviderCode":0},"address":{"postalCode":22300,"provinceCode":"22","cityDescription":"BARBASTRO","addressType":"AVENIDA","addressDescription":"PIRINEOS","addressNumber":11,"doorway":"","floor":"","gateway":"","stair":"","latitude":42.03766,"longitude":0.12942},"contact":{"phone":"974316515","mobilePhone":"","email":"","documentNumber":"B22230056"},"professional":{"gender":"","collegiateCode":0,"collegiateAut":""},"languages":[]},{"providerCode":3570164,"providerLocalicationCode":1298677,"providerName":"POLICLINICA BINEFAR","parentCode":0,"parentDescription":"","networkCode":1,"networkDescription":"","distance":4634.77,"electronicPrescription":false,"appointmentRequired":true,"providerType":4,"doctorType":7,"businessGroup":false,"onlineAppointment":false,"videoConsultation":false,"specialityInfo":{"specialityCode":98,"specialityDescription":"PODOLOGÍA","subSpecialityCode":0,"subSpecialityDescription":"","specialistName":"","specialityProviderCode":0},"address":{"postalCode":22500,"provinceCode":"22","cityDescription":"BINEFAR","addressType":"CALLE","addressDescription":"BENITO COLL","addressNumber":85,"doorway":"","floor":"","gateway":"","stair":"","latitude":41.84724,"longitude":0.29826},"contact":{"phone":"974429851","mobilePhone":"","email":"","documentNumber":"B22230056"},"professional":{"gender":"","collegiateCode":0,"collegiateAut":""},"languages":[]},{"providerCode":2924348,"providerLocalicationCode":870984,"providerName":"MOREU GRACIA, SILVIA","parentCode":0,"parentDescription":"","networkCode":1,"networkDescription":"","distance":4666.51,"electronicPrescription":false,"appointmentRequired":true,"providerType":1,"doctorType":6,"businessGroup":false,"onlineAppointment":false,"videoConsultation":false,"specialityInfo":{"specialityCode":98,"specialityDescription":"PODOLOGÍA","subSpecialityCode":0,"subSpecialityDescription":"","specialistName":"","specialityProviderCode":0},"address":{"postalCode":22004,"provinceCode":"22","cityDescription":"HUESCA","addressType":"AVENIDA","addressDescription":"MARTÍNEZ DE VELASCO","addressNumber":40,"doorway":"","floor":"Bajos","gateway":"","stair":"","latitude":42.1321527,"longitude":-0.4184843},"contact":{"phone":"974212928","mobilePhone":"","email":"","documentNumber":"18040091H"},"professional":{"gender":"H","collegiateCode":838220070,"collegiateAut":""},"languages":[]}]